VisitorsandCOVID.py
VisitorsandCOVID-0.1.3.dist-info/METADATA
VisitorsandCOVID-0.1.3.dist-info/WHEEL
VisitorsandCOVID-0.1.3.dist-info/entry_points.txt
VisitorsandCOVID-0.1.3.dist-info/top_level.txt
VisitorsandCOVID-0.1.3.dist-info/RECORD
