Metadata-Version: 2.1
Name: VisitorsandCOVID
Version: 0.1.3
Summary: This project compares the number of amusement park visitors with COVID infected people.
Home-page: https://github.com/ritakei/VisitorsandCOVID
Author: rinko takei
Author-email: rtakei@sciencepark.co.jp
License: UNKNOWN
Project-URL: Bug Tracker, https://github.com/ritakei/VisitorsandCOVID
Platform: UNKNOWN
Classifier: Programming Language :: Python :: 3
Classifier: License :: OSI Approved :: MIT License
Classifier: Operating System :: OS Independent
Requires-Python: >=3.8.5
